xocr
