Metadata-Version: 2.1
Name: xocr
Version: 1.0.7
Summary: UNKNOWN
Home-page: https://gitee.com/spider-x/xocr
Author: BruceLong
Author-email: 18656170559@163.com
License: MIT Licence
Platform: any
License-File: LICENSE
